README.txt
setup.py
zest/__init__.py
zest.stabilizer.egg-info/PKG-INFO
zest.stabilizer.egg-info/SOURCES.txt
zest.stabilizer.egg-info/dependency_links.txt
zest.stabilizer.egg-info/entry_points.txt
zest.stabilizer.egg-info/namespace_packages.txt
zest.stabilizer.egg-info/not-zip-safe
zest.stabilizer.egg-info/requires.txt
zest.stabilizer.egg-info/top_level.txt
zest/stabilizer/CREDITS.txt
zest/stabilizer/HISTORY.txt
zest/stabilizer/README.txt
zest/stabilizer/TODO.txt
zest/stabilizer/__init__.py
zest/stabilizer/buildoututils.py
zest/stabilizer/needrelease.py
zest/stabilizer/stabilize.py
zest/stabilizer/unstable.py