Metadata-Version: 1.0
Name: zest.stabilizer
Version: 1.2.2
Summary: Script to help move a buildout from unstable to stable
Home-page: http://pypi.python.org/pypi/zest.stabilizer
Author: Reinout and Maurits van Rees
Author-email: reinout@vanrees.org
License: GPL
Platform: UNKNOWN
Classifier: Programming Language :: Python
Classifier: Topic :: Software Development :: Libraries :: Python Modules
